Workbook

Sheet AI Risk Register
A1: ROCKLEDGE BENEFITS ADMINISTRATORS — AI RISK ASSESSMENT (NIST AI RMF MAP / MEASURE)
A2: Risks assessed against NIST AI RMF trustworthiness characteristics and AI 600-1 GenAI risk categories | EU AI Act as amended by Reg. (EU) 2026/1744 (in force 27 Jul 2026) | Assessment date: 2026-08-05 | Fictional organization. Created for portfolio demonstration purposes.
A4: Risk ID | B4: AI System | C4: AI RMF Trustworthiness Characteristic | D4: GenAI Risk Category (AI 600-1) | E4: Risk Description | F4: Harm Type | G4: Affected Population | H4: Inherent Likelihood | I4: Inherent Impact | J4: Inherent Score | K4: Inherent Level | L4: Existing Controls | M4: Residual Likelihood | N4: Residual Impact | O4: Residual Score | P4: Residual Level | Q4: Treatment | R4: Planned Controls / Actions | S4: AI RMF Function | T4: Owner | U4: Target Date
A5: AIR-001 | B5: AI-001 ClaimDesk | C5: Fair — with harmful bias managed | D5: — | E5: Model trained on historical adjudication data may encode past disparities; denial recommendations may differ by protected characteristic proxied through ZIP code and plan type. | F5: Discriminatory outcome; regulatory | G5: Members in 3 EU plans + all US plans | H5: 4 | I5: 5 | J5: =H5*I5 | K5: =IF(J5>=15,"Critical",IF(J5>=10,"High",IF(J5>=5,"Medium","Low"))) | L5: No fairness testing performed; adjuster confirms each recommendation but override rate is 3%, indicating automation bias. | M5: 3 | N5: 5 | O5: =M5*N5 | P5: =IF(O5>=15,"Critical",IF(O5>=10,"High",IF(O5>=5,"Medium","Low"))) | Q5: Mitigate | R5: Commission disparate-impact analysis across protected classes; establish fairness metrics and thresholds; retrain or reweight if thresholds breached; document per EU AI Act Art. 10 data governance. | S5: Measure | T5: VP Claims Operations | U5: 2026-09-23
A6: AIR-002 | B6: AI-001 ClaimDesk | C6: Accountable & Transparent | D6: — | E6: No documented explanation for individual recommendations; members denied benefits cannot receive a meaningful reason beyond the adjuster's note. | F6: Rights; regulatory | G6: Members receiving adverse decisions | H6: 4 | I6: 4 | J6: =H6*I6 | K6: =IF(J6>=15,"Critical",IF(J6>=10,"High",IF(J6>=5,"Medium","Low"))) | L6: Adjuster free-text rationale field (inconsistently completed). | M6: 3 | N6: 4 | O6: =M6*N6 | P6: =IF(O6>=15,"Critical",IF(O6>=10,"High",IF(O6>=5,"Medium","Low"))) | Q6: Mitigate | R6: Implement per-decision feature attribution (SHAP or equivalent) surfaced to adjuster; require structured rationale; align to adverse-action notice requirements. | S6: Manage | T6: VP Claims Operations | U6: 2026-10-21
A7: AIR-003 | B7: AI-001 ClaimDesk | C7: Valid & Reliable | D7: — | E7: Model performance drift as plan rules and provider coding change; no monitoring of live accuracy versus training baseline. | F7: Financial; member harm | G7: All adjudicated claims | H7: 3 | I7: 4 | J7: =H7*I7 | K7: =IF(J7>=15,"Critical",IF(J7>=10,"High",IF(J7>=5,"Medium","Low"))) | L7: Annual retraining; no in-production monitoring. | M7: 2 | N7: 4 | O7: =M7*N7 | P7: =IF(O7>=15,"Critical",IF(O7>=10,"High",IF(O7>=5,"Medium","Low"))) | Q7: Mitigate | R7: Deploy drift monitoring on input distributions and outcome rates; define retraining triggers; monthly performance report to model owner. | S7: Measure | T7: Head of Data Science | U7: 2026-09-21
A8: AIR-004 | B8: AI-001 ClaimDesk | C8: Accountable & Transparent | D8: — | E8: If ClaimDesk is High-Risk under Annex III, it operates for 3 EU client plans without conformity assessment, technical documentation, or database registration. Classification is contested: Annex III(5)(a) covers systems used by or on behalf of public authorities for essential public assistance benefits and (5)(c) covers insurance risk/pricing — neither cleanly covers private claims adjudication. | F8: Regulatory (EU AI Act); contractual | G8: Rockledge; EU clients | H8: 4 | I8: 5 | J8: =H8*I8 | K8: =IF(J8>=15,"Critical",IF(J8>=10,"High",IF(J8>=5,"Medium","Low"))) | L8: None specific to AI Act. Digital Omnibus (Reg. 2026/1744, in force 27 Jul 2026) moved the Annex III deadline to 2 Dec 2027, creating runway that did not exist a month ago. | M8: 4 | N8: 5 | O8: =M8*N8 | P8: =IF(O8>=15,"Critical",IF(O8>=10,"High",IF(O8>=5,"Medium","Low"))) | Q8: Mitigate | R8: Obtain written counsel determination on Annex III applicability by 23 Sep 2026 — this is the gating question. Proceed with fairness and explainability work regardless, since it is required on its merits. See Decision Memo for both classification outcomes. | S8: Govern | T8: General Counsel + VP Claims | U8: 2026-09-23 (counsel determination)
A9: AIR-005 | B9: AI-004 Resume Screener | C9: Fair — with harmful bias managed | D9: — | E9: Third-party ranking model with undisclosed training data; vendor declines to provide bias audit results; Dublin recruiting creates EU high-risk exposure and NYC roles trigger Local Law 144. | F9: Discriminatory outcome; regulatory | G9: Job applicants | H9: 4 | I9: 5 | J9: =H9*I9 | K9: =IF(J9>=15,"Critical",IF(J9>=10,"High",IF(J9>=5,"Medium","Low"))) | L9: Recruiter reviews top 20 only — candidates ranked 21+ never seen by a human. | M9: 4 | N9: 5 | O9: =M9*N9 | P9: =IF(O9>=15,"Critical",IF(O9>=10,"High",IF(O9>=5,"Medium","Low"))) | Q9: Mitigate (pause) | R9: Pause pilot. Require vendor bias audit report and Art. 13 transparency documentation as condition of resumption. If unavailable, terminate. Independent NYC LL144 audit if resumed for NYC roles. | S9: Govern | T9: VP People | U9: 2026-08-21
A10: AIR-006 | B10: AI-002 Chatbot | C10: Valid & Reliable | D10: Confabulation | E10: LLM generates confident but incorrect coverage answers; member acts on wrong deductible or network information. | F10: Financial harm to member; reputational | G10: Members using chatbot | H10: 4 | I10: 3 | J10: =H10*I10 | K10: =IF(J10>=15,"Critical",IF(J10>=10,"High",IF(J10>=5,"Medium","Low"))) | L10: RAG grounding on plan docs; no output verification; escalation button. | M10: 3 | N10: 3 | O10: =M10*N10 | P10: =IF(O10>=15,"Critical",IF(O10>=10,"High",IF(O10>=5,"Medium","Low"))) | Q10: Mitigate | R10: Implement grounded-citation requirement (answer must cite plan document section); confabulation test suite run on release; weekly sample audit of coverage answers; auto-escalate on low-confidence. | S10: Measure | T10: Director of Member Services | U10: 2026-09-23
A11: AIR-007 | B11: AI-002 Chatbot | C11: Accountable & Transparent | D11: Human-AI Configuration | E11: Members not clearly informed they are interacting with AI. Art. 50 transparency duties were expressly NOT deferred by the Digital Omnibus and applied from 2 Aug 2026 — this obligation is live now, unlike the Annex III high-risk duties. | F11: Regulatory (AI Act Art. 50 transparency); trust | G11: Members using chatbot | H11: 5 | I11: 2 | J11: =H11*I11 | K11: =IF(J11>=15,"Critical",IF(J11>=10,"High",IF(J11>=5,"Medium","Low"))) | L11: Small footer text. | M11: 2 | N11: 2 | O11: =M11*N11 | P11: =IF(O11>=15,"Critical",IF(O11>=10,"High",IF(O11>=5,"Medium","Low"))) | Q11: Mitigate | R11: Prominent disclosure at session start; persistent AI indicator; easy path to human. Lowest effort item in the register and the only one already past its legal deadline. Do this first. | S11: Manage | T11: Director of Member Services | U11: 2026-08-21 (Art. 50 duty already applied 2026-08-02)
A12: AIR-008 | B12: AI-002 Chatbot | C12: Secure & Resilient | D12: Information Security | E12: Prompt injection via member-submitted text could extract system prompt or induce off-policy responses; RAG index includes documents with internal notes. | F12: Data exposure; abuse | G12: Rockledge; members | H12: 3 | I12: 4 | J12: =H12*I12 | K12: =IF(J12>=15,"Critical",IF(J12>=10,"High",IF(J12>=5,"Medium","Low"))) | L12: Azure content filters (default). | M12: 2 | N12: 3 | O12: =M12*N12 | P12: =IF(O12>=15,"Critical",IF(O12>=10,"High",IF(O12>=5,"Medium","Low"))) | Q12: Mitigate | R12: Red-team with OWASP LLM Top 10 test cases; scrub RAG index to member-facing documents only; input/output filtering; log and alert on injection signatures. | S12: Measure | T12: CISO | U12: 2026-09-23
A13: AIR-009 | B13: AI-007 M365 Copilot | C13: Privacy-Enhanced | D13: Data Privacy | E13: Copilot indexes SharePoint libraries containing PHI; users can surface member records they lack a need to know via natural-language query. | F13: Privacy breach (HIPAA); regulatory | G13: Members; Rockledge | H13: 4 | I13: 5 | J13: =H13*I13 | K13: =IF(J13>=15,"Critical",IF(J13>=10,"High",IF(J13>=5,"Medium","Low"))) | L13: SharePoint permissions (over-broad in legacy sites). | M13: 2 | N13: 4 | O13: =M13*N13 | P13: =IF(O13>=15,"Critical",IF(O13>=10,"High",IF(O13>=5,"Medium","Low"))) | Q13: Mitigate | R13: Restrict Copilot semantic index from PHI-classified sites; sensitivity labels + DLP for AI-generated content; access recertification on legacy libraries first. | S13: Manage | T13: CIO | U13: 2026-09-21
A14: AIR-010 | B14: AI-009 Shadow AI | C14: Privacy-Enhanced | D14: Data Privacy | E14: Staff pasting member data into consumer AI tools; no contractual protection, potential training-data ingestion. | F14: Privacy breach; regulatory | G14: Members | H14: 5 | I14: 4 | J14: =H14*I14 | K14: =IF(J14>=15,"Critical",IF(J14>=10,"High",IF(J14>=5,"Medium","Low"))) | L14: None. | M14: 2 | N14: 3 | O14: =M14*N14 | P14: =IF(O14>=15,"Critical",IF(O14>=10,"High",IF(O14>=5,"Medium","Low"))) | Q14: Mitigate | R14: AI acceptable use policy; CASB block on consumer AI endpoints; sanctioned enterprise alternative (AI-007) with data protections; awareness campaign; monitor CASB for residual usage. | S14: Govern | T14: CISO | U14: 2026-08-25
A15: AIR-011 | B15: AI-003 Fraud Detector | C15: Explainable & Interpretable | D15: — | E15: Vendor model flags claims with no reason code; SIU cannot explain to providers why payment was delayed; risk of unfair provider treatment. | F15: Provider relations; potential regulatory | G15: Providers; members with delayed claims | H15: 3 | I15: 3 | J15: =H15*I15 | K15: =IF(J15>=15,"Critical",IF(J15>=10,"High",IF(J15>=5,"Medium","Low"))) | L15: SIU reviews every flag before action. | M15: 2 | N15: 3 | O15: =M15*N15 | P15: =IF(O15>=15,"Critical",IF(O15>=10,"High",IF(O15>=5,"Medium","Low"))) | Q15: Accept (with monitoring) | R15: Request reason-code feature from vendor at renewal; track flag-to-confirmed-fraud rate by provider type quarterly to detect systematic skew. Human review already prevents automated adverse action. | S15: Measure | T15: Director of SIU | U15: 2026-12-22
A16: AIR-012 | B16: Program-wide | C16: Accountable & Transparent | D16: — | E16: No AI governance function, policy, or accountable executive; decisions about AI use made ad hoc by business units. | F16: Organizational; all AI risks compound | G16: Rockledge | H16: 5 | I16: 4 | J16: =H16*I16 | K16: =IF(J16>=15,"Critical",IF(J16>=10,"High",IF(J16>=5,"Medium","Low"))) | L16: None. | M16: 2 | N16: 3 | O16: =M16*N16 | P16: =IF(O16>=15,"Critical",IF(O16>=10,"High",IF(O16>=5,"Medium","Low"))) | Q16: Mitigate | R16: Establish AI Governance Committee (chair: General Counsel; members: CISO, CIO, Chief Actuary, VP People, Compliance); adopt AI policy; assign system owners; quarterly review cadence. Foundation for ISO/IEC 42001 alignment. | S16: Govern | T16: General Counsel | U16: 2026-08-25
A17: AIR-013 | B17: AI-008 Actuarial Forecast | C17: Valid & Reliable | D17: — | E17: The aggregate claims-cost model could be reused to price or assess individual members without anyone reassessing it. Applied that way it would fall under Annex III(5)(c), and its validation covers aggregate projections only. | F17: Regulatory (EU AI Act); member pricing harm | G17: Members, if scope changes | H17: 2 | I17: 4 | J17: =H17*I17 | K17: =IF(J17>=15,"Critical",IF(J17>=10,"High",IF(J17>=5,"Medium","Low"))) | L17: Annual model validation; Chief Actuary review of outputs. | M17: 1 | N17: 4 | O17: =M17*N17 | P17: =IF(O17>=15,"Critical",IF(O17>=10,"High",IF(O17>=5,"Medium","Low"))) | Q17: Mitigate | R17: Add a scope-change gate: any proposal to use AI-008 at the individual level triggers an AI risk reassessment and a counsel classification before build work starts. | S17: Govern | T17: Chief Actuary | U17: 2026-10-26

Sheet Trustworthiness Coverage
A1: COVERAGE BY NIST AI RMF TRUSTWORTHINESS CHARACTERISTIC
A2: Which characteristics the register addresses, and how many risks each carries. Gaps in coverage are as informative as high counts.
A4: Characteristic | B4: # Risks | C4: Highest Residual Level | D4: Note
A5: Valid & Reliable | B5: =COUNTIF('AI Risk Register'!$C$5:$C$17,A5) | C5: =IF(COUNTIFS('AI Risk Register'!$C$5:$C$17,A5,'AI Risk Register'!$P$5:$P$17,"Critical")>0,"Critical",IF(COUNTIFS('AI Risk Register'!$C$5:$C$17,A5,'AI Risk Register'!$P$5:$P$17,"High")>0,"High",IF(COUNTIFS('AI Risk Register'!$C$5:$C$17,A5,'AI Risk Register'!$P$5:$P$17,"Medium")>0,"Medium",IF(B5=0,"—","Low")))) | D5: Performance, accuracy, drift
A6: Safe | B6: =COUNTIF('AI Risk Register'!$C$5:$C$17,A6) | C6: =IF(COUNTIFS('AI Risk Register'!$C$5:$C$17,A6,'AI Risk Register'!$P$5:$P$17,"Critical")>0,"Critical",IF(COUNTIFS('AI Risk Register'!$C$5:$C$17,A6,'AI Risk Register'!$P$5:$P$17,"High")>0,"High",IF(COUNTIFS('AI Risk Register'!$C$5:$C$17,A6,'AI Risk Register'!$P$5:$P$17,"Medium")>0,"Medium",IF(B6=0,"—","Low")))) | D6: Physical/psychological safety — no direct exposure in this inventory
A7: Secure & Resilient | B7: =COUNTIF('AI Risk Register'!$C$5:$C$17,A7) | C7: =IF(COUNTIFS('AI Risk Register'!$C$5:$C$17,A7,'AI Risk Register'!$P$5:$P$17,"Critical")>0,"Critical",IF(COUNTIFS('AI Risk Register'!$C$5:$C$17,A7,'AI Risk Register'!$P$5:$P$17,"High")>0,"High",IF(COUNTIFS('AI Risk Register'!$C$5:$C$17,A7,'AI Risk Register'!$P$5:$P$17,"Medium")>0,"Medium",IF(B7=0,"—","Low")))) | D7: Adversarial robustness, prompt injection
A8: Accountable & Transparent | B8: =COUNTIF('AI Risk Register'!$C$5:$C$17,A8) | C8: =IF(COUNTIFS('AI Risk Register'!$C$5:$C$17,A8,'AI Risk Register'!$P$5:$P$17,"Critical")>0,"Critical",IF(COUNTIFS('AI Risk Register'!$C$5:$C$17,A8,'AI Risk Register'!$P$5:$P$17,"High")>0,"High",IF(COUNTIFS('AI Risk Register'!$C$5:$C$17,A8,'AI Risk Register'!$P$5:$P$17,"Medium")>0,"Medium",IF(B8=0,"—","Low")))) | D8: Documentation, disclosure, governance
A9: Explainable & Interpretable | B9: =COUNTIF('AI Risk Register'!$C$5:$C$17,A9) | C9: =IF(COUNTIFS('AI Risk Register'!$C$5:$C$17,A9,'AI Risk Register'!$P$5:$P$17,"Critical")>0,"Critical",IF(COUNTIFS('AI Risk Register'!$C$5:$C$17,A9,'AI Risk Register'!$P$5:$P$17,"High")>0,"High",IF(COUNTIFS('AI Risk Register'!$C$5:$C$17,A9,'AI Risk Register'!$P$5:$P$17,"Medium")>0,"Medium",IF(B9=0,"—","Low")))) | D9: Reason codes, attribution
A10: Privacy-Enhanced | B10: =COUNTIF('AI Risk Register'!$C$5:$C$17,A10) | C10: =IF(COUNTIFS('AI Risk Register'!$C$5:$C$17,A10,'AI Risk Register'!$P$5:$P$17,"Critical")>0,"Critical",IF(COUNTIFS('AI Risk Register'!$C$5:$C$17,A10,'AI Risk Register'!$P$5:$P$17,"High")>0,"High",IF(COUNTIFS('AI Risk Register'!$C$5:$C$17,A10,'AI Risk Register'!$P$5:$P$17,"Medium")>0,"Medium",IF(B10=0,"—","Low")))) | D10: Data minimization, PHI exposure
A11: Fair — with harmful bias managed | B11: =COUNTIF('AI Risk Register'!$C$5:$C$17,A11) | C11: =IF(COUNTIFS('AI Risk Register'!$C$5:$C$17,A11,'AI Risk Register'!$P$5:$P$17,"Critical")>0,"Critical",IF(COUNTIFS('AI Risk Register'!$C$5:$C$17,A11,'AI Risk Register'!$P$5:$P$17,"High")>0,"High",IF(COUNTIFS('AI Risk Register'!$C$5:$C$17,A11,'AI Risk Register'!$P$5:$P$17,"Medium")>0,"Medium",IF(B11=0,"—","Low")))) | D11: Disparate impact

Sheet Method
A1: METHOD & LIMITATIONS
A3: Framework basis | B3: NIST AI RMF 1.0 organizes AI risk into four functions (Govern, Map, Measure, Manage) and seven trustworthiness characteristics. Each risk is tagged to the characteristic it threatens and the function that owns its treatment. Generative-AI risks additionally reference NIST AI 600-1's twelve GenAI risk categories (confabulation, data privacy, information security, human-AI configuration, etc.).
A4: Why tag to characteristics | B4: It exposes coverage gaps. A register with eight fairness risks and zero security risks tells you the assessors' expertise, not the organization's exposure. The Trustworthiness Coverage tab is the check.
A5: Scoring | B5: 5x5 qualitative, likelihood × impact. Ordinal, not cardinal — same limitation as any risk matrix. Adequate for prioritizing thirteen risks; inadequate for comparing spend across them. Impact anchored to harm type: a discriminatory-outcome risk at 5 is a different kind of severe than a financial risk at 5.
A6: What is different about AI risk | B6: Three things. (1) Harms are frequently to third parties — members, applicants — rather than to the organization, so the risk owner and the harmed party diverge. (2) Bias and drift are emergent: the system can be compliant at deployment and non-compliant six months later with no code change. (3) Human oversight is often nominal — a 3% override rate on AI-001 means the human is ratifying, not reviewing. Automation bias is itself a risk.
A7: Relationship to the inventory | B7: Every risk maps to an AI ID in the AI System Inventory. AIR-012 (no governance function) is program-wide and is the root cause behind several system-specific risks.
A8: Relationship to the decision memo | B8: AIR-004 and AIR-005 are the two risks that cannot be treated by controls alone — they require a business decision about whether to continue the use case. Those decisions are documented in the accompanying memo, not here.
A9: Regulatory status as assessed | B9: The Digital Omnibus on AI (Regulation (EU) 2026/1744) was published in the Official Journal on 24 July 2026 and entered into force on 27 July 2026. It defers Annex III standalone high-risk obligations from 2 August 2026 to 2 December 2027, and Annex I embedded high-risk systems to 2 August 2028. It does NOT defer Article 50 transparency duties, the Article 5 prohibitions, or GPAI provider obligations. The deferral is therefore selective, and treating it as a blanket extension is the error to avoid.
A10: Why the deferral does not reduce urgency here | B10: Two reasons. First, the one obligation that is live now — Art. 50 transparency, AIR-007 — is the one we had not met. Second, AIR-001 (encoded bias in denial recommendations) has no compliance date attached to it. The model either discriminates or it does not, and we currently cannot say which. Deadlines govern enforcement, not harm.
A11: Contested classification | B11: AIR-004 turns on whether ClaimDesk falls within Annex III. It is not clearly enumerated: (5)(a) addresses systems used by or on behalf of public authorities to evaluate eligibility for essential public assistance benefits, and (5)(c) addresses risk assessment and pricing for life and health insurance. A private administrator adjudicating employer-sponsored benefit claims sits between them; the open question under (5)(a) is whether Rockledge acts on behalf of a public authority. The register treats it as high-risk pending counsel determination, which is the conservative posture, and the Decision Memo presents both outcomes.
A12: Not legal advice | B12: EU AI Act tiering and obligations are stated for demonstration. Real applicability requires counsel.
